backup_uploader/__init__.py
backup_uploader/chain.py
backup_uploader/cli.py
backup_uploader/directories.py
backup_uploader/parser.py
backup_uploader/clients/__init__.py
backup_uploader/clients/base.py
backup_uploader/clients/dropbox.py
backup_uploader/clients/exceptions.py
backup_uploader/clients/mega.py
backup_uploader-0.5.0.dist-info/LICENSE
backup_uploader-0.5.0.dist-info/METADATA
backup_uploader-0.5.0.dist-info/WHEEL
backup_uploader-0.5.0.dist-info/entry_points.txt
backup_uploader-0.5.0.dist-info/top_level.txt
backup_uploader-0.5.0.dist-info/RECORD
