Metadata-Version: 2.1
Name: backup-uploader
Version: 0.5.0
Summary: UNKNOWN
Home-page: https://github.com/aspedrosa/BackupsUploader
Author: André Pedrosa
Author-email: aspedr0sa@protonmail.com
License: MIT
Keywords: backup,uploader
Platform: UNKNOWN
Classifier: Development Status :: 4 - Beta
Classifier: Intended Audience :: Developers
Classifier: License :: OSI Approved :: MIT License
Classifier: Natural Language :: English
Classifier: Programming Language :: Python
Classifier: Programming Language :: Python :: 3
Classifier: Programming Language :: Python :: 3.6
Classifier: Programming Language :: Python :: 3.7
Classifier: Programming Language :: Python :: 3.8
Classifier: Programming Language :: Python :: 3.9
Classifier: Programming Language :: Python :: 3 :: Only
Classifier: Topic :: Utilities
License-File: LICENSE
Requires-Dist: click
Provides-Extra: dropbox
Requires-Dist: dropbox ; extra == 'dropbox'
Provides-Extra: mega
Requires-Dist: mega.py ; extra == 'mega'
